<?xml version="1.0" encoding="UTF-8"?>
<LanguageData>
  
  <!-- EN: snake -->
  <Snake.label>أفعى</Snake.label>
  <!-- EN: left lung -->
  <Snake.corePart.parts.left_lung.customLabel>الرئة اليسرى</Snake.corePart.parts.left_lung.customLabel>
  <!-- EN: right lung -->
  <Snake.corePart.parts.right_lung.customLabel>الرئة اليمنى</Snake.corePart.parts.right_lung.customLabel>
  <!-- EN: left kidney -->
  <Snake.corePart.parts.left_kidney.customLabel>الكلية اليسرى</Snake.corePart.parts.left_kidney.customLabel>
  <!-- EN: right kidney -->
  <Snake.corePart.parts.right_kidney.customLabel>الكلية اليمنى</Snake.corePart.parts.right_kidney.customLabel>
  <!-- EN: left eye -->
  <Snake.corePart.parts.SnakeHead.parts.left_eye.customLabel>العين اليسرى</Snake.corePart.parts.SnakeHead.parts.left_eye.customLabel>
  <!-- EN: right eye -->
  <Snake.corePart.parts.SnakeHead.parts.right_eye.customLabel>العين اليمنى</Snake.corePart.parts.SnakeHead.parts.right_eye.customLabel>
  
</LanguageData>