<?xml version="1.0" encoding="UTF-8"?>
<LanguageData>
  
  <!-- EN: beam -->
  <BeamBypassShields.label>شعاع</BeamBypassShields.label>
  <!-- EN: {0} has been beamed to death. -->
  <BeamBypassShields.deathMessage>مات {0} متأثراً بالأشعة.</BeamBypassShields.deathMessage>
  
  <!-- EN: bullet -->
  <Bullet_TraitIncendiary.label>رصاصة</Bullet_TraitIncendiary.label>
  <!-- EN: {0} has been shot to death. -->
  <Bullet_TraitIncendiary.deathMessage>مات {0} متأثراً بطلق ناري.</Bullet_TraitIncendiary.deathMessage>
  
  <!-- EN: bullet -->
  <Bullet_TraitTox.label>رصاصة</Bullet_TraitTox.label>
  <!-- EN: {0} has been shot to death. -->
  <Bullet_TraitTox.deathMessage>مات {0} متأثراً بطلق ناري.</Bullet_TraitTox.deathMessage>
  
</LanguageData>