<?xml version="1.0" encoding="UTF-8"?>
<LanguageData>
  
  <!-- EN: bite -->
  <Bite.label>عضة</Bite.label>
  
  <!-- EN: blunt -->
  <Blunt.label>ضربة خفيفة</Blunt.label>
  
  <!-- EN: cut -->
  <Cut.label>قطع</Cut.label>
  
  <!-- EN: demolish -->
  <Demolish.label>هدم</Demolish.label>
  
  <!-- EN: kick material in eyes -->
  <KickMaterialInEyes.label>ركل مادة في العيون</KickMaterialInEyes.label>
  
  <!-- EN: poke -->
  <Poke.label>نكز</Poke.label>
  
  <!-- EN: scratch -->
  <Scratch.label>خدش</Scratch.label>
  
  <!-- EN: toxic scratch -->
  <ScratchToxic.label>خدش سام</ScratchToxic.label>
  
  <!-- EN: stab -->
  <Stab.label>طعن</Stab.label>
  
  <!-- EN: toxic bite -->
  <ToxicBite.label>عضة سامة</ToxicBite.label>
  
</LanguageData>