<?xml version="1.0" encoding="UTF-8"?>
<LanguageData>
  
  <!-- EN: thrumbomane -->
  <Leather_AlphaThrumbo.label>ثرومبومان</Leather_AlphaThrumbo.label>
  <!-- EN: The furry pelt of an alpha thrumbo. It is extraordinarily durable and luxurious - one can almost feel a psychic echo of the animal's ancient story through the gossamer fur.\n\nIt is used for the highest-quality crafts for its insulation and strength. -->
  <Leather_AlphaThrumbo.description>الفراء الكثيف لثرومبو ألفا. إنه متين وفاخر بشكل استثنائي - يكاد المرء يشعر بصدى نفسي لقصة الحيوان القديمة من خلال الفراء الناعم.\n\nيُستخدم في أرقى الحرف اليدوية لعزله وقوته.</Leather_AlphaThrumbo.description>
  
  <!-- EN: armadillo leather -->
  <Leather_Armadillo.label>جلد مدرع</Leather_Armadillo.label>
  <!-- EN: Tanned, dried, scraped armadillo skin. It's tough, but offers little protection against the elements. -->
  <Leather_Armadillo.description>جلد مدرع مدبوغ ومجفف ومكشوط. إنه قاسٍ، لكنه يوفر حماية قليلة ضد العوامل الجوية.</Leather_Armadillo.description>
  
  <!-- EN: hippo leather -->
  <Leather_Hippo.label>جلد فرس النهر</Leather_Hippo.label>
  <!-- EN: Tanned, dried, scraped hippo skin. While extremely durable, it provides little protection from extreme weather. -->
  <Leather_Hippo.description>جلد فرس النهر مدبوغ ومجفف ومكشوط. رغم أنه متين للغاية، إلا أنه يوفر حماية قليلة من الطقس القاسي.</Leather_Hippo.description>
  
  <!-- EN: mastodon leather -->
  <Leather_Mastodon.label>جلد ماستودون</Leather_Mastodon.label>
  <!-- EN: Tanned, dried, scraped mastodon skin. It's tough and an excellent insulator against the cold. -->
  <Leather_Mastodon.description>جلد ماستودون مدبوغ ومجفف ومكشوط. إنه قاسٍ وعازل ممتاز ضد البرد.</Leather_Mastodon.description>
  
  <!-- EN: mink fur -->
  <Leather_Mink.label>فراء المنك</Leather_Mink.label>
  <!-- EN: Tanned, dried, scraped mink skin. Soft, sleek, and subtly luxurious, mink is used in premium winter clothing and high-end furnishings, meaning it fetches a high price. -->
  <Leather_Mink.description>جلد المنك مدبوغ ومجفف ومكشوط. ناعم وأملس وفاخر بشكل خفي، يُستخدم المنك في الملابس الشتوية الفاخرة والمفروشات الراقية، مما يعني أنه يجلب سعراً مرتفعاً.</Leather_Mink.description>
  
  <!-- EN: sealskin -->
  <Leather_Sealskin.label>جلد الفقمة</Leather_Sealskin.label>
  <!-- EN: The tanned skin of various pinnipeds, such as seals, sea lions, and walruses. It's not particularly tough but it is extremely well insulated. Sealskin is luxuriously soft to the touch, fetching a high price. -->
  <Leather_Sealskin.description>الجلد المدبوغ لزعنفيات الأقدام المختلفة، مثل الفقمات وأسود البحر والفظ. إنه ليس قاسياً بشكل خاص لكنه معزول بشكل ممتاز. جلد الفقمة ناعم بشكل فاخر عند اللمس، ويجلب سعراً مرتفعاً.</Leather_Sealskin.description>
  
</LanguageData>