<?xml version="1.0" encoding="UTF-8"?>
<LanguageData>
  
  <!-- EN: cyclops -->
  <Mech_Cyclops.label>سايكلوبس</Mech_Cyclops.label>
  <!-- EN: A front-line combat mechanoid named for its large optical array. The cyclops specializes in counter-shield attacks. It takes a long time to lock onto a target, but once locked on, it fires a near endless barrage of shield-piercing beams. -->
  <Mech_Cyclops.description>ميكانويد قتالي في الخطوط الأمامية سمي بمصفوفته البصرية الكبيرة. يتخصص السايكلوبس في الهجمات المضادة للدروع. يستغرق وقتاً طويلاً لتثبيت الهدف، لكن بمجرد التثبيت، يطلق وابلاً شبه لا نهائي من الأشعة الخارقة للدروع.</Mech_Cyclops.description>
  <!-- EN: front left leg -->
  <Mech_Cyclops.tools.front_left_leg.label>الساق الأمامية اليسرى</Mech_Cyclops.tools.front_left_leg.label>
  <!-- EN: leg -->
  <Mech_Cyclops.tools.front_left_leg.labelNoLocation>ساق</Mech_Cyclops.tools.front_left_leg.labelNoLocation>
  <!-- EN: front right leg -->
  <Mech_Cyclops.tools.front_right_leg.label>الساق الأمامية اليمنى</Mech_Cyclops.tools.front_right_leg.label>
  <!-- EN: leg -->
  <Mech_Cyclops.tools.front_right_leg.labelNoLocation>ساق</Mech_Cyclops.tools.front_right_leg.labelNoLocation>
  <!-- EN: head -->
  <Mech_Cyclops.tools.head.label>رأس</Mech_Cyclops.tools.head.label>
  
</LanguageData>