<?xml version="1.0" encoding="UTF-8"?>
<LanguageData>
  
  <!-- EN: mechanitor -->
  <Mechanitor.label>ميكانيتور</Mechanitor.label>
  <Mechanitor.labelFemale>ميكانيتورة</Mechanitor.labelFemale>
  <Mechanitor.labelPlural>ميكانيتوريون</Mechanitor.labelPlural>
  
  <!-- EN: mechanitor -->
  <Mechanitor_Basic.label>ميكانيتور</Mechanitor_Basic.label>
  <Mechanitor_Basic.labelFemale>ميكانيتورة</Mechanitor_Basic.labelFemale>
  <Mechanitor_Basic.labelPlural>ميكانيتوريون</Mechanitor_Basic.labelPlural>
  
  <!-- EN: sanguophage -->
  <Sanguophage.label>سانغوفاج</Sanguophage.label>
  <Sanguophage.labelFemale>سانغوفاجة</Sanguophage.labelFemale>
  <Sanguophage.labelPlural>سانغوفاجيون</Sanguophage.labelPlural>
  
  <!-- EN: sanguophage -->
  <Sanguophage_Player.label>سانغوفاج</Sanguophage_Player.label>
  <Sanguophage_Player.labelFemale>سانغوفاجة</Sanguophage_Player.labelFemale>
  <Sanguophage_Player.labelPlural>سانغوفاجيون</Sanguophage_Player.labelPlural>
  
  <!-- EN: thrall -->
  <SanguophageThrall.label>تابع</SanguophageThrall.label>
  <SanguophageThrall.labelFemale>تابعة</SanguophageThrall.labelFemale>
  <SanguophageThrall.labelPlural>أتباع</SanguophageThrall.labelPlural>
  
  <!-- EN: villager -->
  <Tribal_Child.label>قروي</Tribal_Child.label>
  <Tribal_Child.labelFemale>قروية</Tribal_Child.labelFemale>
  <Tribal_Child.labelPlural>قرويون</Tribal_Child.labelPlural>
  
  <!-- EN: villager -->
  <Villager_Child.label>قروي</Villager_Child.label>
  <Villager_Child.labelFemale>قروية</Villager_Child.labelFemale>
  <Villager_Child.labelPlural>قرويون</Villager_Child.labelPlural>
  
</LanguageData>
