<?xml version="1.0" encoding="UTF-8"?>
<LanguageData>
  
  <!-- EN: abandoned landmark -->
  <AbandonedLandmark.label>معلم مهجور</AbandonedLandmark.label>
  <!-- EN: An abandoned campsite at a landmark. -->
  <AbandonedLandmark.description>موقع تخييم مهجور عند معلم.</AbandonedLandmark.description>
  
  <!-- EN: basic asteroid -->
  <AsteroidBasic.label>كويكب أساسي</AsteroidBasic.label>
  <!-- EN: A vacstone asteroid that was towed into orbit around the planet as part of a mining operation long ago. Most of the valuable resources have been depleted from this asteroid.\n\nThis location can be reached using transport pods, shuttles, or a gravship. -->
  <AsteroidBasic.description>كويكب من حجر الفراغ تم قطره إلى مدار حول الكوكب كجزء من عملية تعدين منذ زمن بعيد. معظم الموارد القيمة قد استنفدت من هذا الكويكب.\n\nيمكن الوصول إلى هذا الموقع باستخدام كبسولات النقل، أو المكوكات، أو سفينة الجاذبية.</AsteroidBasic.description>
  
  <!-- EN: asteroid mining site -->
  <AsteroidMiningSite.label>موقع تعدين كويكب</AsteroidMiningSite.label>
  <!-- EN: A vacstone asteroid that was towed into orbit around the planet as part of a mining operation long ago. This asteroid has only been partially mined.\n\nThis location can be reached using transport pods, shuttles, or a gravship. -->
  <AsteroidMiningSite.description>كويكب من حجر الفراغ تم قطره إلى مدار حول الكوكب كجزء من عملية تعدين منذ زمن بعيد. هذا الكويكب لم يتم تعدينه إلا جزئياً.\n\nيمكن الوصول إلى هذا الموقع باستخدام كبسولات النقل، أو المكوكات، أو سفينة الجاذبية.</AsteroidMiningSite.description>
  
  <!-- EN: claimable site -->
  <ClaimableSite.label>موقع يمكن المطالبة به</ClaimableSite.label>
  
  <!-- EN: claimable space site -->
  <ClaimableSpaceSite.label>موقع فضائي يمكن المطالبة به</ClaimableSpaceSite.label>
  
  <!-- EN: destroyed settlement -->
  <DestroyedSpaceSettlement.label>مستوطنة مدمرة</DestroyedSpaceSettlement.label>
  <!-- EN: A destroyed settlement. -->
  <DestroyedSpaceSettlement.description>مستوطنة مدمرة.</DestroyedSpaceSettlement.description>
  
  <!-- EN: gravship -->
  <Gravship.label>سفينة الجاذبية</Gravship.label>
  <!-- EN: A gravship in flight. -->
  <Gravship.description>سفينة جاذبية في حالة طيران.</Gravship.description>
  
  <!-- EN: gravship launch -->
  <GravshipLaunch.label>إطلاق سفينة الجاذبية</GravshipLaunch.label>
  <!-- EN: The launch site of a gravship. -->
  <GravshipLaunch.description>موقع إطلاق سفينة الجاذبية.</GravshipLaunch.description>
  
  <!-- EN: mechhive -->
  <Mechhive.label>خلية ميكانويد</Mechhive.label>
  
  <!-- EN: orbital item stash -->
  <OrbitalItemStash.label>مخبأ عناصر مداري</OrbitalItemStash.label>
  <!-- EN: A vacstone asteroid that was towed into orbit around the planet as part of a mining operation long ago. Most of the valuable resources have been depleted from this asteroid.\n\nThis location can be reached using transport pods, shuttles, or a gravship. -->
  <OrbitalItemStash.description>كويكب من حجر الفراغ تم قطره إلى مدار حول الكوكب كجزء من عملية تعدين منذ زمن بعيد. معظم الموارد القيمة قد استنفدت من هذا الكويكب.\n\nيمكن الوصول إلى هذا الموقع باستخدام كبسولات النقل، أو المكوكات، أو سفينة الجاذبية.</OrbitalItemStash.description>
  
  <!-- EN: passenger shuttle -->
  <PassengerShuttle.label>مكوك ركاب</PassengerShuttle.label>
  <!-- EN: A passenger shuttle in flight. -->
  <PassengerShuttle.description>مكوك ركاب في حالة طيران.</PassengerShuttle.description>
  
  <!-- EN: space -->
  <Space.label>الفضاء</Space.label>
  
  <!-- EN: orbital settlement -->
  <SpaceSettlement.label>مستوطنة مدارية</SpaceSettlement.label>
  <!-- EN: An orbital platform controlled by another human faction. They won't appreciate visitors.\n\nThese platforms have long-range automatic weapon systems capable of destroying incoming ships. They can only safely be approached by a gravship with a signal jammer. -->
  <SpaceSettlement.description>منصة مدارية تتحكم بها فصيلة بشرية أخرى. لن يرحبوا بالزوار.\n\nتحتوي هذه المنصات على أنظمة أسلحة آلية بعيدة المدى قادرة على تدمير السفن القادمة. لا يمكن الاقتراب منها بأمان إلا بواسطة سفينة جاذبية مزودة بمشوش إشارة.</SpaceSettlement.description>
  
  <!-- EN: space site -->
  <SpaceSite.label>موقع فضائي</SpaceSite.label>
  
</LanguageData>
